setup.cfg
setup.py
xtd/__init__.py
xtd.egg-info/PKG-INFO
xtd.egg-info/SOURCES.txt
xtd.egg-info/dependency_links.txt
xtd.egg-info/requires.txt
xtd.egg-info/top_level.txt
xtd/core/__init__.py
xtd/core/application.py
xtd/core/error.py
xtd/core/mixin.py
xtd/core/config/__init__.py
xtd/core/config/checkers.py
xtd/core/config/formatter.py
xtd/core/config/manager.py
xtd/core/logger/__init__.py
xtd/core/logger/filter.py
xtd/core/logger/formatter.py
xtd/core/logger/manager.py
xtd/core/logger/tools.py
xtd/core/param/__init__.py
xtd/core/param/manager.py
xtd/core/stat/__init__.py
xtd/core/stat/counter.py
xtd/core/stat/handler.py
xtd/core/stat/manager.py
xtd/core/tools/__init__.py
xtd/core/tools/daemonize.py
xtd/core/tools/mergedicts.py
xtd/core/tools/thread.py
xtd/core/tools/url.py
xtd/network/__init__.py
xtd/network/client/__init__.py
xtd/network/client/asynclient.py
xtd/network/server/__init__.py
xtd/network/server/application.py
xtd/network/server/config.py
xtd/network/server/counter.py
xtd/network/server/log.py
xtd/network/server/manager.py
xtd/network/server/param.py
xtd/network/server/tools.py