Metadata-Version: 1.1
Name: xtd
Version: 0.5.8
Summary: High level library to quickly build strong python apps
Home-page: https://github.com/psycofdj/xtdpy
Author: Xavier MARCELET
Author-email: xavier@marcelet.com
License: UNKNOWN
Download-URL: https://github.com/psycofdj/xtdpy/tarball/0.5.8
Keywords: xtd,python,library,high-level
Platform: UNKNOWN
Classifier: Development Status :: 2 - Pre-Alpha
Classifier: Environment :: Console
Classifier: Intended Audience :: Developers
Classifier: License :: OSI Approved :: GNU General Public License v3 (GPLv3)
Classifier: Operating System :: Unix
Classifier: Programming Language :: Python :: 3 :: Only
Classifier: Topic :: Software Development :: Libraries :: Python Modules
